VeriSlicer/Error_designs/error_design_3_3/.ipynb_checkpoints/design_3-checkpoint.v
`default_nettype none

module sha1_w_mem(
                  input wire           clk,
                  input wire           reset_n,

                  input wire [511 : 0] block,

                  input wire           init,
                  input wire           next,

                  output wire [31 : 0] w
                 );
  reg [31 : 0] w_mem [0 : 15];
  reg [31 : 0] w_mem00_new;
  reg [31 : 0] w_mem01_new;
  reg [31 : 0] w_mem02_new;
  reg [31 : 0] w_mem03_new;
  reg [31 : 0] w_mem04_new;
  reg [31 : 0] w_mem05_new;
  reg [31 : 0] w_mem06_new;
  reg [31 : 0] w_mem07_new;
  reg [31 : 0] w_mem08_new;
  reg [31 : 0] w_mem09_new;
  reg [31 : 0] w_mem10_new;
  reg [31 : 0] w_mem11_new;
  reg [31 : 0] w_mem12_new;
  reg [31 : 0] w_mem13_new;
  reg [31 : 0] w_mem14_new;
  reg [31 : 0] w_mem15_new;
  reg          w_mem_we;

  reg [6 : 0] w_ctr_reg;
  reg [6 : 0] w_ctr_new;
  reg         w_ctr_we;
  reg [31 : 0] w_tmp;
  reg [31 : 0] w_new;
  assign w = w_tmp;
  always @ (posedge clk or negedge reset_n)
    begin : reg_update
      integer i;

      if (!reset_n)
        begin
          for (i = 0 ; i < 16 ; i = i + 1)
            w_mem[i] <= 32'h0;

          w_ctr_reg <= 7'h0;
        end
      else
        begin
          if (w_mem_we)
            begin
              w_mem[00] <= w_mem00_new;
              w_mem[01] <= w_mem01_new;
              w_mem[02] <= w_mem02_new;
              w_mem[03] <= w_mem03_new;
              w_mem[04] <= w_mem04_new;
              w_mem[05] <= w_mem05_new;
              w_mem[06] <= w_mem06_new;
              w_mem[07] <= w_mem07_new;
              w_mem[08] <= w_mem08_new;
              w_mem[09] <= w_mem09_new;
              w_mem[10] <= w_mem10_new;
              w_mem[11] <= w_mem11_new;
              w_mem[12] <= w_mem12_new;
              w_mem[13] <= w_mem13_new;
              w_mem[14] <= w_mem14_new;
              w_mem[15] <= w_mem15_new;
            end

          if (w_ctr_we)
            w_ctr_reg <= w_ctr_new;
        end
    end
  always @*
    begin : select_w
      if (w_ctr_reg < 16)
        w_tmp = w_mem[w_ctr_reg[3 : 0]];
      else
        w_tmp = w_new;
    end
  always @*
    begin : w_mem_update_logic
      reg [31 : 0] w_0;
      reg [31 : 0] w_2;
      reg [31 : 0] w_8;
      reg [31 : 0] w_13;
      reg [31 : 0] w_16;

      w_mem00_new = 32'h0;
      w_mem01_new = 32'h0;
      w_mem02_new = 32'h0;
      w_mem03_new = 32'h0;
      w_mem04_new = 32'h0;
      w_mem05_new = 32'h0;
      w_mem06_new = 32'h0;
      w_mem07_new = 32'h0;
      w_mem08_new = 32'h0;
      w_mem09_new = 32'h0;
      w_mem10_new = 32'h0;
      w_mem11_new = 32'h0;
      w_mem12_new = 32'h0;
      w_mem13_new = 32'h0;
      w_mem14_new = 32'h0;
      w_mem15_new = 32'h0;
      w_mem_we    = 1'h0;

      w_0   = w_mem[0];
      w_2   = w_mem[2];
      w_8   = w_mem[8];
      w_13  = w_mem[13];
      w_16  = w_13 ^ w_8 ^ w_2 ^ w_0;
      w_new = {w_16[30 : 0], w_16[31]};

      if (init)
        begin
          w_mem00_new = block[511 : 480];
          w_mem01_new = block[479 : 448];
          w_mem02_new = block[447 : 416];
          w_mem03_new = block[415 : 384];
          w_mem04_new = block[383 : 352];
          w_mem05_new = block[351 : 320];
          w_mem06_new = block[319 : 288];
          w_mem07_new = block[287 : 256];
          w_mem08_new = block[255 : 224];
          w_mem09_new = block[223 : 192];
          w_mem10_new = block[191 : 160];
          w_mem11_new = block[159 : 128];
          w_mem12_new = block[127 :  96];
          w_mem13_new = block[95  :  64];
          w_mem14_new = block[63  :  32];
          w_mem15_new = block[31  :   0];
          w_mem_we    = 1'h1;
        end

      if (next && (w_ctr_reg > 15))
        begin
          w_mem00_new = w_mem[01];
          w_mem01_new = w_mem[02];
          w_mem02_new = w_mem[03];
          w_mem03_new = w_mem[04];
          w_mem04_new = w_mem[05];
          w_mem05_new = w_mem[06];
          w_mem06_new = w_mem[07];
          w_mem07_new = w_mem[08];
          w_mem08_new = w_mem[09];
          w_mem09_new = w_mem[10];
          w_mem10_new = w_mem[11];
          w_mem11_new = w_mem[12];
          w_mem12_new = w_mem[13];
          w_mem13_new = w_mem[14];
          w_mem14_new = w_mem[15];
          w_mem15_new = w_new;
          w_mem_we    = 1'h1;
        end
    end
  always @*
    begin : w_ctr
      w_ctr_new = 7'h0;
      w_ctr_we  = 1'h0;

      if (init)
        begin
          w_ctr_new = 7'h0;
          w_ctr_we  = 1'h1;
        end

      if (next)
        begin
          w_ctr_new = w_ctr_reg + 7'h01;
          w_ctr_we  = 1'h1;
        end
    end
endmodule

`default_nettype none

module sha1_core(
                 input wire            clk,
                 input wire            reset_n,

                 input wire            init,
                 input wire            next,

                 input wire [511 : 0]  block,

                 output wire           ready,

                 output wire [159 : 0] digest,
                 output wire           digest_valid
                );
  parameter H0_0 = 32'h67452301;
  parameter H0_1 = 32'hefcdab89;
  parameter H0_2 = 32'h98badcfe;
  parameter H0_3 = 32'h10325476;
  parameter H0_4 = 32'hc3d2e1f0;

  parameter SHA1_ROUNDS = 79;

  parameter CTRL_IDLE   = 0;
  parameter CTRL_ROUNDS = 1;
  parameter CTRL_DONE   = 2;
  reg [31 : 0] a_reg;
  reg [31 : 0] a_new;
  reg [31 : 0] b_reg;
  reg [31 : 0] b_new;
  reg [31 : 0] c_reg;
  reg [31 : 0] c_new;
  reg [31 : 0] d_reg;
  reg [31 : 0] d_new;
  reg [31 : 0] e_reg;
  reg [31 : 0] e_new;
  reg          a_e_we;

  reg [31 : 0] H0_reg;
  reg [31 : 0] H0_new;
  reg [31 : 0] H1_reg;
  reg [31 : 0] H1_new;
  reg [31 : 0] H2_reg;
  reg [31 : 0] H2_new;
  reg [31 : 0] H3_reg;
  reg [31 : 0] H3_new;
  reg [31 : 0] H4_reg;
  reg [31 : 0] H4_new;
  reg          H_we;

  reg [6 : 0] round_ctr_reg;
  reg [6 : 0] round_ctr_new;
  reg         round_ctr_we;
  reg         round_ctr_inc;
  reg         round_ctr_rst;

  reg digest_valid_reg;
  reg digest_valid_new;
  reg digest_valid_we;

  reg [1 : 0] sha1_ctrl_reg;
  reg [1 : 0] sha1_ctrl_new;
  reg         sha1_ctrl_we;
  reg           digest_init;
  reg           digest_update;
  reg           state_init;
  reg           state_update;
  reg           first_block;
  reg           ready_flag;
  reg           w_init;
  reg           w_next;
  wire [31 : 0] w;

  sha1_w_mem w_mem_inst(
                        .clk(clk),
                        .reset_n(reset_n),

                        .block(block),

                        .init(w_init),
                        .next(w_next),

                        .w(w)
                       );
  assign ready        = ready_flag;
  assign digest       = {H0_reg, H1_reg, H2_reg, H3_reg, H4_reg};
  assign digest_valid = digest_valid_reg;
  always @ (posedge clk or negedge reset_n)
    begin : reg_update
      if (!reset_n)
        begin
          a_reg            <= 32'h0;
          b_reg            <= 32'h0;
          c_reg            <= 32'h0;
          d_reg            <= 32'h0;
          e_reg            <= 32'h0;
          H0_reg           <= 32'h0;
          H1_reg           <= 32'h0;
          H2_reg           <= 32'h0;
          H3_reg           <= 32'h0;
          H4_reg           <= 32'h0;
          digest_valid_reg <= 1'h0;
          round_ctr_reg    <= 7'h0;
          sha1_ctrl_reg    <= CTRL_IDLE;
        end
      else
        begin
          if (a_e_we)
            begin
              a_reg <= a_new;
              b_reg <= b_new;
              c_reg <= c_new;
              d_reg <= d_new;
              e_reg <= e_new;
            end

          if (H_we)
            begin
              H0_reg <= H0_new;
              H1_reg <= H1_new;
              H2_reg <= H2_new;
              H3_reg <= H3_new;
              H4_reg <= H4_new;
            end

          if (round_ctr_we)
            round_ctr_reg <= round_ctr_new;

          if (digest_valid_we)
            digest_valid_reg <= digest_valid_new;

          if (sha1_ctrl_we)
            sha1_ctrl_reg <= sha1_ctrl_new;
        end
    end
  always @*
    begin : digest_logic
      H0_new = 32'h0;
      H1_new = 32'h0;
      H2_new = 32'h0;
      H3_new = 32'h0;
      H4_new = 32'h0;
      H_we = 0;

      if (digest_init)
        begin
          H0_new = H0_0;
          H1_new = H0_1;
          H2_new = H0_2;
          H3_new = H0_3;
          H4_new = H0_4;
          H_we = 1;
        end

      if (digest_update)
        begin
          H0_new = H0_reg + a_reg;
          H1_new = H1_reg + b_reg;
          H2_new = H2_reg + c_reg;
          H3_new = H3_reg + d_reg;
          H4_new = H4_reg + e_reg;
          H_we = 1;
        end
    end
  always @*
    begin : state_logic
      reg [31 : 0] a5;
      reg [31 : 0] f;
      reg [31 : 0] k;
      reg [31 : 0] t;

      a5     = 32'h0;
      f      = 32'h0;
      k      = 32'h0;
      t      = 32'h0;
      a_new  = 32'h0;
      b_new  = 32'h0;
      c_new  = 32'h0;
      d_new  = 32'h0;
      e_new  = 32'h0;
      a_e_we = 1'h0;

      if (state_init)
        begin
          if (first_block)
            begin
              a_new  = H0_0;
              b_new  = H0_1;
              c_new  = H0_2;
              d_new  = H0_3;
              e_new  = H0_4;
              a_e_we = 1;
            end
          else
            begin
              a_new  = H0_reg;
              b_new  = H1_reg;
              c_new  = H2_reg;
              d_new  = H3_reg;
              e_new  = H4_reg;
              a_e_we = 1;
            end
        end

      if (state_update)
        begin
          if (round_ctr_reg <= 19)
            begin
              k = 32'h5a827999;
              f =  ((b_reg & c_reg) ^ (~b_reg & d_reg));
            end
          else if ((round_ctr_reg >= 20) && (round_ctr_reg <= 39))
            begin
              k = 32'h6ed9eba1;
              f = b_reg ^ c_reg ^ d_reg;
            end
          else if ((round_ctr_reg >= 40) && (round_ctr_reg <= 59))
            begin
              k = 32'h8f1bbcdc;
              f = ((b_reg | c_reg) ^ (b_reg | d_reg) ^ (c_reg | d_reg));
            end
          else if (round_ctr_reg >= 60)
            begin
              k = 32'hca62c1d6;
              f = b_reg ^ c_reg ^ d_reg;
            end

          a5 = {a_reg[26 : 0], a_reg[31 : 27]};
          t = a5 + e_reg + f + k + w;

          a_new  = t;
          b_new  = a_reg;
          c_new  = {b_reg[1 : 0], b_reg[31 : 2]};
          d_new  = c_reg;
          e_new  = d_reg;
          a_e_we = 1;
        end
    end
  always @*
    begin : round_ctr
      round_ctr_new = 7'h0;
      round_ctr_we  = 1'h0;

      if (round_ctr_rst)
        begin
          round_ctr_new = 7'h0;
          round_ctr_we  = 1'h1;
        end

      if (round_ctr_inc)
        begin
          round_ctr_new = round_ctr_reg + 1'h1;
          round_ctr_we  = 1;
        end
    end
  always @*
    begin : sha1_ctrl_fsm
      digest_init      = 1'h0;
      digest_update    = 1'h0;
      state_init       = 1'h0;
      state_update     = 1'h0;
      first_block      = 1'h0;
      ready_flag       = 1'h0;
      w_init           = 1'h0;
      w_next           = 1'h0;
      round_ctr_inc    = 1'h0;
      round_ctr_rst    = 1'h0;
      digest_valid_new = 1'h0;
      digest_valid_we  = 1'h0;
      sha1_ctrl_new    = CTRL_IDLE;
      sha1_ctrl_we     = 1'h0;

      case (sha1_ctrl_reg)
        CTRL_IDLE:
          begin
            ready_flag = 1;

            if (init)
              begin
                digest_init      = 1'h1;
                w_init           = 1'h1;
                state_init       = 1'h1;
                first_block      = 1'h1;
                round_ctr_rst    = 1'h1;
                digest_valid_new = 1'h0;
                digest_valid_we  = 1'h1;
                sha1_ctrl_new    = CTRL_ROUNDS;
                sha1_ctrl_we     = 1'h1;
              end

            if (next)
              begin
                w_init           = 1'h1;
                state_init       = 1'h1;
                round_ctr_rst    = 1'h1;
                digest_valid_new = 1'h0;
                digest_valid_we  = 1'h1;
                sha1_ctrl_new    = CTRL_ROUNDS;
                sha1_ctrl_we     = 1'h1;
              end
          end


        CTRL_ROUNDS:
          begin
            state_update  = 1'h1;
            round_ctr_inc = 1'h1;
            w_next        = 1'h1;

            if (round_ctr_reg == (SHA1_ROUNDS - 1))
              begin
                sha1_ctrl_new = CTRL_DONE;
                sha1_ctrl_we  = 1'h1;
              end
          end


        CTRL_DONE:
          begin
            digest_update    = 1'h1;
            digest_valid_new = 1'h1;
            digest_valid_we  = 1'h1;
            sha1_ctrl_new    = CTRL_IDLE;
            sha1_ctrl_we     = 1'h1;
          end
      endcase
    end
endmodule

`default_nettype none
module design_3(
            input wire           clk,
            input wire           reset_n,
            input wire           cs,
            input wire           we,
            input wire  [7 : 0]  address,
            input wire  [31 : 0] write_data,
            output wire [31 : 0] read_data,
            output wire          error
           );
  localparam ADDR_NAME0       = 8'h00;
  localparam ADDR_NAME1       = 8'h01;
  localparam ADDR_VERSION     = 8'h02;

  localparam ADDR_CTRL        = 8'h08;
  localparam CTRL_INIT_BIT    = 0;
  localparam CTRL_NEXT_BIT    = 1;

  localparam ADDR_STATUS      = 8'h09;
  localparam STATUS_READY_BIT = 0;
  localparam STATUS_VALID_BIT = 1;

  localparam ADDR_BLOCK0    = 8'h10;
  localparam ADDR_BLOCK15   = 8'h1f;

  localparam ADDR_DIGEST0   = 8'h20;
  localparam ADDR_DIGEST4   = 8'h24;

  localparam CORE_NAME0     = 32'h73686131;
  localparam CORE_NAME1     = 32'h20202020;
  localparam CORE_VERSION   = 32'h302e3630;

  reg init_reg;
  reg init_new;
  reg next_reg;
  reg next_new;
  reg ready_reg;
  reg [31 : 0] block_reg [0 : 15];
  reg          block_we;
  reg [159 : 0] digest_reg;
  reg digest_valid_reg;

  wire           core_ready;
  wire [511 : 0] core_block;
  wire [159 : 0] core_digest;
  wire           core_digest_valid;
  reg [31 : 0]   tmp_read_data;
  reg            tmp_error;

  assign core_block = {block_reg[00], block_reg[01], block_reg[02], block_reg[03],
                       block_reg[04], block_reg[05], block_reg[06], block_reg[07],
                       block_reg[08], block_reg[09], block_reg[10], block_reg[11],
                       block_reg[12], block_reg[13], block_reg[14], block_reg[15]};
  assign read_data = tmp_read_data;
  assign error     = tmp_error;

  sha1_core core(
                 .clk(clk),
                 .reset_n(reset_n),

                 .init(init_reg),
                 .next(next_reg),

                 .block(core_block),

                 .ready(core_ready),

                 .digest(core_digest),
                 .digest_valid(core_digest_valid)
                );
  always @ (posedge clk or negedge reset_n)
    begin : reg_update
      integer i;

      if (!reset_n)
        begin
          init_reg         <= 1'h0;
          next_reg         <= 1'h0;
          ready_reg        <= 1'h0;
          digest_reg       <= 160'h0;
          digest_valid_reg <= 1'h0;

          for (i = 0 ; i < 16 ; i = i + 1)
            block_reg[i] <= 32'h0;
        end
      else
        begin
          ready_reg        <= core_ready;
          digest_valid_reg <= core_digest_valid;
          init_reg         <= init_new;
          next_reg         <= next_new;

          if (block_we)
            block_reg[address[3 : 0]] <= write_data;

          if (core_digest_valid)
            digest_reg <= core_digest;
        end
    end
  always @*
    begin : api
      init_new      = 1'h0;
      next_new      = 1'h0;
      block_we      = 1'h0;
      tmp_read_data = 32'h0;
      tmp_error     = 1'h0;

      if (cs)
        begin
          if (we)
            begin
              if ((address >= ADDR_BLOCK0) && (address <= ADDR_BLOCK15))
                block_we = 1'h1;

              if (address == ADDR_CTRL)
                begin
                  init_new = write_data[CTRL_INIT_BIT];
                  next_new = write_data[CTRL_NEXT_BIT];
                end
            end
          else
            begin
              if ((address >= ADDR_BLOCK0) && (address <= ADDR_BLOCK15))
                tmp_read_data = block_reg[address[3 : 0]];

              if ((address >= ADDR_DIGEST0) && (address <= ADDR_DIGEST4))
                tmp_read_data = digest_reg[(4 - (address - ADDR_DIGEST0)) * 32 +: 32];

              case (address)
                ADDR_NAME0:
                  tmp_read_data = CORE_NAME0;

                ADDR_NAME1:
                  tmp_read_data = CORE_NAME1;

                ADDR_VERSION:
                  tmp_read_data = CORE_VERSION;

                ADDR_CTRL:
                  tmp_read_data = {30'h0, next_reg, init_reg};

                ADDR_STATUS:
                  tmp_read_data = {30'h0, digest_valid_reg, ready_reg};

                default:
                  begin
                    tmp_error = 1'h1;
                  end
              endcase
            end
        end
    end
endmodule

VeriSlicer/Error_designs/error_design_3_1/design_3.vcd
$date
	Sat May 30 10:29:24 2026
$end
$version
	Icarus Verilog
$end
$timescale
	1ps
$end
$scope module design_3 $end
$var wire 8 ! address [7:0] $end
$var wire 1 " clk $end
$var wire 1 # cs $end
$var wire 1 $ error $end
$var wire 32 % read_data [31:0] $end
$var wire 1 & reset_n $end
$var wire 1 ' we $end
$var wire 32 ( write_data [31:0] $end
$var wire 1 ) core_ready $end
$var wire 1 * core_digest_valid $end
$var wire 160 + core_digest [159:0] $end
$var wire 512 , core_block [511:0] $end
$var parameter 8 - ADDR_BLOCK0 $end
$var parameter 8 . ADDR_BLOCK15 $end
$var parameter 8 / ADDR_CTRL $end
$var parameter 8 0 ADDR_DIGEST0 $end
$var parameter 8 1 ADDR_DIGEST4 $end
$var parameter 8 2 ADDR_NAME0 $end
$var parameter 8 3 ADDR_NAME1 $end
$var parameter 8 4 ADDR_STATUS $end
$var parameter 8 5 ADDR_VERSION $end
$var parameter 32 6 CORE_NAME0 $end
$var parameter 32 7 CORE_NAME1 $end
$var parameter 32 8 CORE_VERSION $end
$var parameter 32 9 CTRL_INIT_BIT $end
$var parameter 32 : CTRL_NEXT_BIT $end
$var parameter 32 ; STATUS_READY_BIT $end
$var parameter 32 < STATUS_VALID_BIT $end
$var reg 1 = block_we $end
$var reg 160 > digest_reg [159:0] $end
$var reg 1 ? digest_valid_reg $end
$var reg 1 @ init_new $end
$var reg 1 A init_reg $end
$var reg 1 B next_new $end
$var reg 1 C next_reg $end
$var reg 1 D ready_reg $end
$var reg 1 E tmp_error $end
$var reg 32 F tmp_read_data [31:0] $end
$scope module core $end
$var wire 512 G block [511:0] $end
$var wire 1 " clk $end
$var wire 1 * digest_valid $end
$var wire 1 A init $end
$var wire 1 C next $end
$var wire 1 ) ready $end
$var wire 1 & reset_n $end
$var wire 32 H w [31:0] $end
$var wire 160 I digest [159:0] $end
$var parameter 32 J CTRL_DONE $end
$var parameter 32 K CTRL_IDLE $end
$var parameter 32 L CTRL_ROUNDS $end
$var parameter 32 M H0_0 $end
$var parameter 32 N H0_1 $end
$var parameter 32 O H0_2 $end
$var parameter 32 P H0_3 $end
$var parameter 32 Q H0_4 $end
$var parameter 32 R SHA1_ROUNDS $end
$var reg 32 S H0_new [31:0] $end
$var reg 32 T H0_reg [31:0] $end
$var reg 32 U H1_new [31:0] $end
$var reg 32 V H1_reg [31:0] $end
$var reg 32 W H2_new [31:0] $end
$var reg 32 X H2_reg [31:0] $end
$var reg 32 Y H3_new [31:0] $end
$var reg 32 Z H3_reg [31:0] $end
$var reg 32 [ H4_new [31:0] $end
$var reg 32 \ H4_reg [31:0] $end
$var reg 1 ] H_we $end
$var reg 1 ^ a_e_we $end
$var reg 32 _ a_new [31:0] $end
$var reg 32 ` a_reg [31:0] $end
$var reg 32 a b_new [31:0] $end
$var reg 32 b b_reg [31:0] $end
$var reg 32 c c_new [31:0] $end
$var reg 32 d c_reg [31:0] $end
$var reg 32 e d_new [31:0] $end
$var reg 32 f d_reg [31:0] $end
$var reg 1 g digest_init $end
$var reg 1 h digest_update $end
$var reg 1 i digest_valid_new $end
$var reg 1 j digest_valid_reg $end
$var reg 1 k digest_valid_we $end
$var reg 32 l e_new [31:0] $end
$var reg 32 m e_reg [31:0] $end
$var reg 1 n first_block $end
$var reg 1 o ready_flag $end
$var reg 1 p round_ctr_inc $end
$var reg 7 q round_ctr_new [6:0] $end
$var reg 7 r round_ctr_reg [6:0] $end
$var reg 1 s round_ctr_rst $end
$var reg 1 t round_ctr_we $end
$var reg 2 u sha1_ctrl_new [1:0] $end
$var reg 2 v sha1_ctrl_reg [1:0] $end
$var reg 1 w sha1_ctrl_we $end
$var reg 1 x state_init $end
$var reg 1 y state_update $end
$var reg 1 z w_init $end
$var reg 1 { w_next $end
$scope module w_mem_inst $end
$var wire 512 | block [511:0] $end
$var wire 1 " clk $end
$var wire 1 z init $end
$var wire 1 { next $end
$var wire 1 & reset_n $end
$var wire 32 } w [31:0] $end
$var reg 7 ~ w_ctr_new [6:0] $end
$var reg 7 !" w_ctr_reg [6:0] $end
$var reg 1 "" w_ctr_we $end
$var reg 32 #" w_mem00_new [31:0] $end
$var reg 32 $" w_mem01_new [31:0] $end
$var reg 32 %" w_mem02_new [31:0] $end
$var reg 32 &" w_mem03_new [31:0] $end
$var reg 32 '" w_mem04_new [31:0] $end
$var reg 32 (" w_mem05_new [31:0] $end
$var reg 32 )" w_mem06_new [31:0] $end
$var reg 32 *" w_mem07_new [31:0] $end
$var reg 32 +" w_mem08_new [31:0] $end
$var reg 32 ," w_mem09_new [31:0] $end
$var reg 32 -" w_mem10_new [31:0] $end
$var reg 32 ." w_mem11_new [31:0] $end
$var reg 32 /" w_mem12_new [31:0] $end
$var reg 32 0" w_mem13_new [31:0] $end
$var reg 32 1" w_mem14_new [31:0] $end
$var reg 32 2" w_mem15_new [31:0] $end
$var reg 1 3" w_mem_we $end
$var reg 32 4" w_new [31:0] $end
$var reg 32 5" w_tmp [31:0] $end
$scope begin reg_update $end
$var integer 32 6" i [31:0] $end
$upscope $end
$scope begin select_w $end
$upscope $end
$scope begin w_ctr $end
$upscope $end
$scope begin w_mem_update_logic $end
$var reg 32 7" w_0 [31:0] $end
$var reg 32 8" w_13 [31:0] $end
$var reg 32 9" w_16 [31:0] $end
$var reg 32 :" w_2 [31:0] $end
$var reg 32 ;" w_8 [31:0] $end
$upscope $end
$upscope $end
$scope begin digest_logic $end
$upscope $end
$scope begin reg_update $end
$upscope $end
$scope begin round_ctr $end
$upscope $end
$scope begin sha1_ctrl_fsm $end
$upscope $end
$scope begin state_logic $end
$var reg 32 <" a5 [31:0] $end
$var reg 32 =" f [31:0] $end
$var reg 32 >" k [31:0] $end
$var reg 32 ?" t [31:0] $end
$upscope $end
$upscope $end
$scope begin api $end
$upscope $end
$scope begin reg_update $end
$var integer 32 @" i [31:0] $end
$upscope $end
$upscope $end
$enddefinitions $end
$comment Show the parameter values. $end
$dumpall
b1001111 R
b11000011110100101110000111110000 Q
b10000001100100101010001110110 P
b10011000101110101101110011111110 O
b11101111110011011010101110001001 N
b1100111010001010010001100000001 M
b1 L
b0 K
b10 J
b1 <
b0 ;
b1 :
b0 9
b110000001011100011011000110000 8
b100000001000000010000000100000 7
b1110011011010000110000100110001 6
b10 5
b1001 4
b1 3
b0 2
b100100 1
b100000 0
b1000 /
b11111 .
b10000 -
$end
#0
$dumpvars
b10000 @"
b0 ?"
b0 >"
b0 ="
b0 <"
b0 ;"
b0 :"
b0 9"
b0 8"
b0 7"
b10000 6"
b0 5"
b0 4"
03"
b0 2"
b0 1"
b0 0"
b0 /"
b0 ."
b0 -"
b0 ,"
b0 +"
b0 *"
b0 )"
b0 ("
b0 '"
b0 &"
b0 %"
b0 $"
b0 #"
0""
b0 !"
b0 ~
b0 }
b0 |
0{
0z
0y
0x
0w
b0 v
b0 u
0t
0s
b0 r
b0 q
0p
1o
0n
b0 m
b0 l
0k
0j
0i
0h
0g
b0 f
b0 e
b0 d
b0 c
b0 b
b0 a
b0 `
b0 _
0^
0]
b0 \
b0 [
b0 Z
b0 Y
b0 X
b0 W
b0 V
b0 U
b0 T
b0 S
b0 I
b0 H
b0 G
b0 F
0E
0D
0C
0B
0A
0@
0?
b0 >
0=
b0 ,
b0 +
0*
1)
b0 (
0'
0&
b0 %
0$
0#
1"
b0 !
$end
#1000
0"
#2000
b10000 @"
b10000 6"
1"
#3000
0"
#4000
1=
1'
1#
b1010010110111110101011001100010 (
b10000 !
1D
1"
1&
#5000
0"
#6000
b110101111101010001010100000110 (
b10001 !
1=
b1010010110111110101011001100010000000000000000000000000000000000000000000000000000000000000000000000000000000000000000000000000000000000000000000000000000000000000000000000000000000000000000000000000000000000000000000000000000000000000000000000000000000000000000000000000000000000000000000000000000000000000000000000000000000000000000000000000000000000000000000000000000000000000000000000000000000000000000000000000000000000000000000000000000000000000000000000000000000000000000000000000000000000000000000000000 ,
b1010010110111110101011001100010000000000000000000000000000000000000000000000000000000000000000000000000000000000000000000000000000000000000000000000000000000000000000000000000000000000000000000000000000000000000000000000000000000000000000000000000000000000000000000000000000000000000000000000000000000000000000000000000000000000000000000000000000000000000000000000000000000000000000000000000000000000000000000000000000000000000000000000000000000000000000000000000000000000000000000000000000000000000000000000000 G
b1010010110111110101011001100010000000000000000000000000000000000000000000000000000000000000000000000000000000000000000000000000000000000000000000000000000000000000000000000000000000000000000000000000000000000000000000000000000000000000000000000000000000000000000000000000000000000000000000000000000000000000000000000000000000000000000000000000000000000000000000000000000000000000000000000000000000000000000000000000000000000000000000000000000000000000000000000000000000000000000000000000000000000000000000000000 |
1"
#7000
0"
#8000
b1100010001000010101011110011100 (
b10010 !
1=
b1010010110111110101011001100010001101011111010100010101000001100000000000000000000000000000000000000000000000000000000000000000000000000000000000000000000000000000000000000000000000000000000000000000000000000000000000000000000000000000000000000000000000000000000000000000000000000000000000000000000000000000000000000000000000000000000000000000000000000000000000000000000000000000000000000000000000000000000000000000000000000000000000000000000000000000000000000000000000000000000000000000000000000000000000000000 ,
b1010010110111110101011001100010001101011111010100010101000001100000000000000000000000000000000000000000000000000000000000000000000000000000000000000000000000000000000000000000000000000000000000000000000000000000000000000000000000000000000000000000000000000000000000000000000000000000000000000000000000000000000000000000000000000000000000000000000000000000000000000000000000000000000000000000000000000000000000000000000000000000000000000000000000000000000000000000000000000000000000000000000000000000000000000000 G
b1010010110111110101011001100010001101011111010100010101000001100000000000000000000000000000000000000000000000000000000000000000000000000000000000000000000000000000000000000000000000000000000000000000000000000000000000000000000000000000000000000000000000000000000000000000000000000000000000000000000000000000000000000000000000000000000000000000000000000000000000000000000000000000000000000000000000000000000000000000000000000000000000000000000000000000000000000000000000000000000000000000000000000000000000000000 |
1"
#9000
0"
#10000
b1000011000011001011111010111010 (
b10011 !
1=
b1010010110111110101011001100010001101011111010100010101000001100110001000100001010101111001110000000000000000000000000000000000000000000000000000000000000000000000000000000000000000000000000000000000000000000000000000000000000000000000000000000000000000000000000000000000000000000000000000000000000000000000000000000000000000000000000000000000000000000000000000000000000000000000000000000000000000000000000000000000000000000000000000000000000000000000000000000000000000000000000000000000000000000000000000000000 ,
b1010010110111110101011001100010001101011111010100010101000001100110001000100001010101111001110000000000000000000000000000000000000000000000000000000000000000000000000000000000000000000000000000000000000000000000000000000000000000000000000000000000000000000000000000000000000000000000000000000000000000000000000000000000000000000000000000000000000000000000000000000000000000000000000000000000000000000000000000000000000000000000000000000000000000000000000000000000000000000000000000000000000000000000000000000000 G
b1010010110111110101011001100010001101011111010100010101000001100110001000100001010101111001110000000000000000000000000000000000000000000000000000000000000000000000000000000000000000000000000000000000000000000000000000000000000000000000000000000000000000000000000000000000000000000000000000000000000000000000000000000000000000000000000000000000000000000000000000000000000000000000000000000000000000000000000000000000000000000000000000000000000000000000000000000000000000000000000000000000000000000000000000000000 |
1"
#11000
0"
#12000
b110001100100101011001011100000 (
b10100 !
1=
b1010010110111110101011001100010001101011111010100010101000001100110001000100001010101111001110001000011000011001011111010111010000000000000000000000000000000000000000000000000000000000000000000000000000000000000000000000000000000000000000000000000000000000000000000000000000000000000000000000000000000000000000000000000000000000000000000000000000000000000000000000000000000000000000000000000000000000000000000000000000000000000000000000000000000000000000000000000000000000000000000000000000000000000000000000000 ,
b1010010110111110101011001100010001101011111010100010101000001100110001000100001010101111001110001000011000011001011111010111010000000000000000000000000000000000000000000000000000000000000000000000000000000000000000000000000000000000000000000000000000000000000000000000000000000000000000000000000000000000000000000000000000000000000000000000000000000000000000000000000000000000000000000000000000000000000000000000000000000000000000000000000000000000000000000000000000000000000000000000000000000000000000000000000 G
b1010010110111110101011001100010001101011111010100010101000001100110001000100001010101111001110001000011000011001011111010111010000000000000000000000000000000000000000000000000000000000000000000000000000000000000000000000000000000000000000000000000000000000000000000000000000000000000000000000000000000000000000000000000000000000000000000000000000000000000000000000000000000000000000000000000000000000000000000000000000000000000000000000000000000000000000000000000000000000000000000000000000000000000000000000000 |
1"
#13000
0"
#14000
b1101000011110110000100111010000 (
b10101 !
1=
b1010010110111110101011001100010001101011111010100010101000001100110001000100001010101111001110001000011000011001011111010111010001100011001001010110010111000000000000000000000000000000000000000000000000000000000000000000000000000000000000000000000000000000000000000000000000000000000000000000000000000000000000000000000000000000000000000000000000000000000000000000000000000000000000000000000000000000000000000000000000000000000000000000000000000000000000000000000000000000000000000000000000000000000000000000000 ,
b1010010110111110101011001100010001101011111010100010101000001100110001000100001010101111001110001000011000011001011111010111010001100011001001010110010111000000000000000000000000000000000000000000000000000000000000000000000000000000000000000000000000000000000000000000000000000000000000000000000000000000000000000000000000000000000000000000000000000000000000000000000000000000000000000000000000000000000000000000000000000000000000000000000000000000000000000000000000000000000000000000000000000000000000000000000 G
b1010010110111110101011001100010001101011111010100010101000001100110001000100001010101111001110001000011000011001011111010111010001100011001001010110010111000000000000000000000000000000000000000000000000000000000000000000000000000000000000000000000000000000000000000000000000000000000000000000000000000000000000000000000000000000000000000000000000000000000000000000000000000000000000000000000000000000000000000000000000000000000000000000000000000000000000000000000000000000000000000000000000000000000000000000000 |
1"
#15000
0"
